setup.py
startour_iq_lib/__init__.py
startour_iq_lib/startour_iq_lib.py
startour_iq_lib.egg-info/PKG-INFO
startour_iq_lib.egg-info/SOURCES.txt
startour_iq_lib.egg-info/dependency_links.txt
startour_iq_lib.egg-info/not-zip-safe
startour_iq_lib.egg-info/top_level.txt