Metadata-Version: 2.1
Name: startour-iq-lib
Version: 0.5
Summary: stars are good
Author: Divyanshi
License: UNKNOWN
Platform: UNKNOWN
